analytics_reporting_client/__init__.py
analytics_reporting_client/api_wrapper.py
analytics_reporting_client/missing_credentials_error.py
analytics_reporting_client/session.py
analytics_reporting_client/tests.py
analytics_reporting_client-0.1.dist-info/METADATA
analytics_reporting_client-0.1.dist-info/RECORD
analytics_reporting_client-0.1.dist-info/WHEEL
analytics_reporting_client-0.1.dist-info/top_level.txt
analytics_reporting_client-0.1.dist-info/zip-safe
